setup.py
bin/vacuum
vacuum/__init__.py
vacuum/api.py
vacuum/config.py
vacuum/datatype.py
vacuum/history.py
vacuum/log.py
vacuum/logme.py
vacuum/notifiy.py
vacuum/parse.py
vacuum.egg-info/PKG-INFO
vacuum.egg-info/SOURCES.txt
vacuum.egg-info/dependency_links.txt
vacuum.egg-info/requires.txt
vacuum.egg-info/top_level.txt
vacuum/third_party/__init__.py
vacuum/third_party/ucpaas.py
vacuum/third_party/submail/__init__.py
vacuum/third_party/submail/address_book_mail.py
vacuum/third_party/submail/address_book_mail_subscribe.py
vacuum/third_party/submail/address_book_mail_unsubscribe.py
vacuum/third_party/submail/address_book_message.py
vacuum/third_party/submail/address_book_message_subscribe.py
vacuum/third_party/submail/address_book_message_unsubscribe.py
vacuum/third_party/submail/app_configs.py
vacuum/third_party/submail/mail.py
vacuum/third_party/submail/mail_send.py
vacuum/third_party/submail/mail_send_demo.py
vacuum/third_party/submail/mail_xsend.py
vacuum/third_party/submail/mail_xsend_demo.py
vacuum/third_party/submail/message.py
vacuum/third_party/submail/message_xsend.py
vacuum/third_party/submail/message_xsend_demo.py