Metadata-Version: 1.0
Name: vacuum
Version: 0.3.1
Summary: JJ Bob
Home-page: UNKNOWN
Author: duoshoubang
Author-email: UNKNOWN
License: UNKNOWN
Platform: UNKNOWN
